.gitignore
.travis.yml
MANIFEST.in
README.rst
bootstrap.py
buildout.cfg
setup.cfg
setup.py
collective/__init__.py
collective.portlet.content.egg-info/PKG-INFO
collective.portlet.content.egg-info/SOURCES.txt
collective.portlet.content.egg-info/dependency_links.txt
collective.portlet.content.egg-info/entry_points.txt
collective.portlet.content.egg-info/namespace_packages.txt
collective.portlet.content.egg-info/not-zip-safe
collective.portlet.content.egg-info/requires.txt
collective.portlet.content.egg-info/top_level.txt
collective/portlet/__init__.py
collective/portlet/content/__init__.py
collective/portlet/content/configure.zcml
collective/portlet/content/contentportlet.pt
collective/portlet/content/contentportlet.py
collective/portlet/content/vocabularies.py
collective/portlet/content/locales/collective.portlet.content.pot
collective/portlet/content/locales/plone.pot
collective/portlet/content/locales/runi18ndude.sh
collective/portlet/content/locales/de/LC_MESSAGES/collective.portlet.content.po
collective/portlet/content/locales/de/LC_MESSAGES/plone.po
collective/portlet/content/locales/it/LC_MESSAGES/collective.portlet.content.po
collective/portlet/content/locales/it/LC_MESSAGES/plone.po
collective/portlet/content/profiles/default/metadata.xml
collective/portlet/content/profiles/default/portlets.xml
collective/portlet/content/tests/__init__.py
collective/portlet/content/tests/base.py
collective/portlet/content/tests/test_portlet.py
docs/HISTORY.txt
docs/INSTALL.txt
docs/LICENSE.GPL
docs/LICENSE.txt
docs/TODO.txt