Metadata-Version: 1.1
Name: collective.portlet.content
Version: 1.8.1
Summary: A Plone portlet that shows a content item.
Home-page: https://github.com/collective/collective.portlet.content
Author: Plone Foundation
Author-email: plone-developers@lists.sourceforge.net
License: GPL
Keywords: plone portlet
Platform: UNKNOWN
Classifier: Framework :: Plone
Classifier: Programming Language :: Python
Classifier: Programming Language :: Python :: 2.6
Classifier: Programming Language :: Python :: 2.7
Classifier: Topic :: Software Development :: Libraries :: Python Modules
